{
  "id": "quote",
  "type": "SharedSlice",
  "name": "Quote",
  "description": "Quote",
  "variations": [
    {
      "id": "default-slice",
      "name": "Default slice",
      "docURL": "...",
      "version": "sktwi1xtmkfgx8626",
      "description": "Quote",
      "primary": {
        "quotetext": {
          "type": "StructuredText",
          "config": {
            "label": "Quote Text",
            "placeholder": "This is where it all begins...",
            "allowTargetBlank": true,
            "single": "paragraph"
          }
        }
      },
      "items": {}
    },
    {
      "id": "quoteReference",
      "name": "Quote Reference",
      "docURL": "...",
      "version": "sktwi1xtmkfgx8626",
      "description": "Quote",
      "primary": {
        "quotetext": {
          "type": "StructuredText",
          "config": {
            "label": "Quote Text",
            "placeholder": "This is where it all begins...",
            "allowTargetBlank": true,
            "single": "paragraph"
          }
        },
        "reference": {
          "config": {
            "label": "reference",
            "placeholder": "",
            "allowTargetBlank": true,
            "single": "paragraph,hyperlink,em,strong"
          },
          "type": "StructuredText"
        }
      },
      "items": {}
    }
  ]
}